haskellian/asyn/iter/__init__.py
haskellian/asyn/iter/managed.py
haskellian/asyn/iter/iter/__init__.py
haskellian/asyn/iter/iter/funcs.py
haskellian/asyn/iter/iter/iter.py
haskellian/asyn/iter/ops/__init__.py
haskellian/asyn/iter/ops/ops.py
haskellian/asyn/iter/ops/prefetching.py
haskellian_asyn_iter-0.1.5.dist-info/METADATA
haskellian_asyn_iter-0.1.5.dist-info/WHEEL
haskellian_asyn_iter-0.1.5.dist-info/top_level.txt
haskellian_asyn_iter-0.1.5.dist-info/RECORD
