Metadata-Version: 2.1
Name: haskellian-asyn-iter
Version: 0.1.5
Summary: FP-style tools for async iterables
Author-email: Marcel Claramunt <marcel@moveread.com>
Project-URL: repo, https://github.com/moveread/REPO.git
Requires-Python: >=3.10
Requires-Dist: haskellian-asyn
